{"trial_id": "4991b09ce59a560ea66c646ae2629fb8", "hyperparameters": {"space": [{"class_name": "Int", "config": {"name": "input_00", "default": null, "conditions": [], "min_value": 1, "max_value": 64, "step": 4, "sampling": null}}, {"class_name": "Int", "config": {"name": "num_layers", "default": null, "conditions": [], "min_value": 1, "max_value": 32, "step": 1, "sampling": null}}, {"class_name": "Int", "config": {"name": "hidden_00", "default": null, "conditions": [], "min_value": 1, "max_value": 64, "step": 4, "sampling": null}}, {"class_name": "Float", "config": {"name": "dropout", "default": 0.0, "conditions": [], "min_value": 0.0, "max_value": 0.5, "step": 0.1, "sampling": null}}, {"class_name": "Choice", "config": {"name": "learning_rate", "default": 0.1, "conditions": [], "values": [0.1, 0.01, 0.001, 0.0001], "ordered": true}}, {"class_name": "Int", "config": {"name": "hidden_01", "default": null, "conditions": [], "min_value": 1, "max_value": 64, "step": 4, "sampling": null}}, {"class_name": "Int", "config": {"name": "hidden_02", "default": null, "conditions": [], "min_value": 1, "max_value": 64, "step": 4, "sampling": null}}, {"class_name": "Int", "config": {"name": "hidden_03", "default": null, "conditions": [], "min_value": 1, "max_value": 64, "step": 4, "sampling": null}}, {"class_name": "Int", "config": {"name": "hidden_04", "default": null, "conditions": [], "min_value": 1, "max_value": 64, "step": 4, "sampling": null}}, {"class_name": "Int", "config": {"name": "hidden_05", "default": null, "conditions": [], "min_value": 1, "max_value": 64, "step": 4, "sampling": null}}, {"class_name": "Int", "config": {"name": "hidden_06", "default": null, "conditions": [], "min_value": 1, "max_value": 64, "step": 4, "sampling": null}}, {"class_name": "Int", "config": {"name": "hidden_07", "default": null, "conditions": [], "min_value": 1, "max_value": 64, "step": 4, "sampling": null}}, {"class_name": "Int", "config": {"name": "hidden_08", "default": null, "conditions": [], "min_value": 1, "max_value": 64, "step": 4, "sampling": null}}, {"class_name": "Int", "config": {"name": "hidden_09", "default": null, "conditions": [], "min_value": 1, "max_value": 64, "step": 4, "sampling": null}}, {"class_name": "Int", "config": {"name": "hidden_10", "default": null, "conditions": [], "min_value": 1, "max_value": 64, "step": 4, "sampling": null}}, {"class_name": "Int", "config": {"name": "hidden_11", "default": null, "conditions": [], "min_value": 1, "max_value": 64, "step": 4, "sampling": null}}, {"class_name": "Int", "config": {"name": "hidden_12", "default": null, "conditions": [], "min_value": 1, "max_value": 64, "step": 4, "sampling": null}}, {"class_name": "Int", "config": {"name": "hidden_13", "default": null, "conditions": [], "min_value": 1, "max_value": 64, "step": 4, "sampling": null}}, {"class_name": "Int", "config": {"name": "hidden_14", "default": null, "conditions": [], "min_value": 1, "max_value": 64, "step": 4, "sampling": null}}, {"class_name": "Int", "config": {"name": "hidden_15", "default": null, "conditions": [], "min_value": 1, "max_value": 64, "step": 4, "sampling": null}}, {"class_name": "Int", "config": {"name": "hidden_16", "default": null, "conditions": [], "min_value": 1, "max_value": 64, "step": 4, "sampling": null}}, {"class_name": "Int", "config": {"name": "hidden_17", "default": null, "conditions": [], "min_value": 1, "max_value": 64, "step": 4, "sampling": null}}, {"class_name": "Int", "config": {"name": "hidden_18", "default": null, "conditions": [], "min_value": 1, "max_value": 64, "step": 4, "sampling": null}}, {"class_name": "Int", "config": {"name": "hidden_19", "default": null, "conditions": [], "min_value": 1, "max_value": 64, "step": 4, "sampling": null}}, {"class_name": "Int", "config": {"name": "hidden_20", "default": null, "conditions": [], "min_value": 1, "max_value": 64, "step": 4, "sampling": null}}, {"class_name": "Int", "config": {"name": "hidden_21", "default": null, "conditions": [], "min_value": 1, "max_value": 64, "step": 4, "sampling": null}}, {"class_name": "Int", "config": {"name": "hidden_22", "default": null, "conditions": [], "min_value": 1, "max_value": 64, "step": 4, "sampling": null}}, {"class_name": "Int", "config": {"name": "hidden_23", "default": null, "conditions": [], "min_value": 1, "max_value": 64, "step": 4, "sampling": null}}, {"class_name": "Int", "config": {"name": "hidden_24", "default": null, "conditions": [], "min_value": 1, "max_value": 64, "step": 4, "sampling": null}}, {"class_name": "Int", "config": {"name": "hidden_25", "default": null, "conditions": [], "min_value": 1, "max_value": 64, "step": 4, "sampling": null}}, {"class_name": "Int", "config": {"name": "hidden_26", "default": null, "conditions": [], "min_value": 1, "max_value": 64, "step": 4, "sampling": null}}, {"class_name": "Int", "config": {"name": "hidden_27", "default": null, "conditions": [], "min_value": 1, "max_value": 64, "step": 4, "sampling": null}}, {"class_name": "Int", "config": {"name": "hidden_28", "default": null, "conditions": [], "min_value": 1, "max_value": 64, "step": 4, "sampling": null}}, {"class_name": "Int", "config": {"name": "hidden_29", "default": null, "conditions": [], "min_value": 1, "max_value": 64, "step": 4, "sampling": null}}], "values": {"input_00": 53, "num_layers": 30, "hidden_00": 13, "dropout": 0.1, "learning_rate": 0.01, "hidden_01": 13, "hidden_02": 9, "hidden_03": 25, "hidden_04": 61, "hidden_05": 13, "hidden_06": 41, "hidden_07": 17, "hidden_08": 37, "hidden_09": 41, "hidden_10": 25, "hidden_11": 53, "hidden_12": 9, "hidden_13": 53, "hidden_14": 33, "hidden_15": 61, "hidden_16": 45, "hidden_17": 9, "hidden_18": 49, "hidden_19": 1, "hidden_20": 1, "hidden_21": 1, "hidden_22": 1, "hidden_23": 1, "hidden_24": 1, "hidden_25": 1, "hidden_26": 1, "hidden_27": 1, "hidden_28": 1, "hidden_29": 1}}, "metrics": {"metrics": {"loss": {"direction": "min", "observations": [{"value": [8249.775390625], "step": 0}]}, "mean_squared_error": {"direction": "min", "observations": [{"value": [8249.775390625], "step": 0}]}, "val_loss": {"direction": "min", "observations": [{"value": [8090.600423177083], "step": 0}]}, "val_mean_squared_error": {"direction": "min", "observations": [{"value": [8090.600423177083], "step": 0}]}}}, "score": 8090.600423177083, "best_step": 0, "status": "COMPLETED"}